dirmaptree/__init__.py
dirmaptree/map.py
dirmaptree-0.1.2.dist-info/METADATA
dirmaptree-0.1.2.dist-info/WHEEL
dirmaptree-0.1.2.dist-info/entry_points.txt
dirmaptree-0.1.2.dist-info/RECORD
