Metadata-Version: 2.3
Name: dirmaptree
Version: 0.1.2
Summary: A clean directory tree generator with customizable exclusions and comments
License: MIT
Author: Shahzer Baig
Author-email: shahzer.baig@gmail.com
Requires-Python: >=3.11
Classifier: License :: OSI Approved :: MIT License
Classifier: Programming Language :: Python :: 3
Classifier: Programming Language :: Python :: 3.11
Classifier: Programming Language :: Python :: 3.12
Classifier: Programming Language :: Python :: 3.13
